{"date":"2026-02-11","type":"originals","posts":[{"id":808293804401639400,"post_url":"https://www.tumblr.com/blog/view/goodtransgirl/808293804401639424","type":"text","is_reblog":false,"added_content":false,"notes":38,"npd":0.83,"start_date":"Feb 11, 2026","days":46,"tags":["shitposting","shitpost","meme","memes","trans meme","trans memes","lgbt meme","lgbt memes","queer meme","queer memes","sapphic meme","sapphic memes"],"title":"#shitposting #shitpost #meme"},{"id":808290023223017500,"post_url":"https://www.tumblr.com/blog/view/goodtransgirl/808290023223017472","type":"text","is_reblog":false,"added_content":false,"notes":101,"npd":2.2,"start_date":"Feb 11, 2026","days":46,"tags":["shitposting","shitpost","meme","memes","trans meme","trans memes","lgbt meme","lgbt memes","queer meme","queer memes","sapphic meme","sapphic memes"],"title":"~SL"},{"id":808286245392384000,"post_url":"https://www.tumblr.com/blog/view/goodtransgirl/808286245392384000","type":"text","is_reblog":false,"added_content":false,"notes":22,"npd":0.48,"start_date":"Feb 11, 2026","days":46,"tags":["shitposting","shitpost","meme","memes","trans meme","trans memes","lgbt meme","lgbt memes","queer meme","queer memes","transgender","lgbtq"],"title":"<img src=\"https://64.media.tumblr.com/7753ffc752c195741b1a6733bbd7eaed/f0b29f2e6edd0dd2-73…"},{"id":808254601698607100,"post_url":"https://www.tumblr.com/blog/view/goodtransgirl/808254601698607104","type":"text","is_reblog":false,"added_content":false,"notes":5,"npd":0.11,"start_date":"Feb 11, 2026","days":46,"tags":["gtg updates","Alexandria Updates"],"title":"Good morning, Alexandria Friends! Happy Wednesday!Ya girl was up late last night, but got …"},{"id":808210749758603300,"post_url":"https://www.tumblr.com/blog/view/goodtransgirl/808210749758603264","type":"text","is_reblog":false,"added_content":false,"notes":19,"npd":0.41,"start_date":"Feb 10, 2026","days":47,"tags":["shitposting","shitpost","meme","memes","trans meme","trans memes","lgbt meme","lgbt memes","queer meme","queer memes","transgender","lgbtq"],"title":"#shitposting #shitpost #meme"}]}