{"date":"2026-03-01","type":"reblogs","posts":[{"id":809927561388982300,"post_url":"https://www.tumblr.com/blog/view/goodtransgirl/809927561388982272","type":"text","is_reblog":true,"added_content":false,"notes":72,"npd":0.87,"start_date":"Feb 28, 2026","days":29,"tags":[],"delta":1},{"id":809923289596248000,"post_url":"https://www.tumblr.com/blog/view/goodtransgirl/809923289596248064","type":"text","is_reblog":true,"added_content":false,"notes":33,"npd":0,"start_date":"Feb 27, 2026","days":30,"tags":[],"delta":0},{"id":809918937610502100,"post_url":"https://www.tumblr.com/blog/view/goodtransgirl/809918937610502144","type":"text","is_reblog":true,"added_content":false,"notes":158,"npd":0,"start_date":"Feb 27, 2026","days":30,"tags":[],"delta":0},{"id":809914593203961900,"post_url":"https://www.tumblr.com/blog/view/goodtransgirl/809914593203961856","type":"text","is_reblog":true,"added_content":false,"notes":134,"npd":0,"start_date":"Feb 26, 2026","days":31,"tags":[],"delta":0},{"id":809910316604457000,"post_url":"https://www.tumblr.com/blog/view/goodtransgirl/809910316604456961","type":"text","is_reblog":true,"added_content":false,"notes":369,"npd":0,"start_date":"Feb 25, 2026","days":32,"tags":[],"delta":0},{"id":809905917769498600,"post_url":"https://www.tumblr.com/blog/view/goodtransgirl/809905917769498624","type":"text","is_reblog":true,"added_content":false,"notes":12,"npd":0,"start_date":"Feb 25, 2026","days":32,"tags":[],"delta":0},{"id":809905549515849700,"post_url":"https://www.tumblr.com/blog/view/goodtransgirl/809905549515849728","type":"text","is_reblog":true,"added_content":false,"notes":31117,"npd":0,"start_date":"Mar 1, 2026","days":28,"tags":[],"delta":0},{"id":809901636716757000,"post_url":"https://www.tumblr.com/blog/view/goodtransgirl/809901636716756992","type":"text","is_reblog":true,"added_content":false,"notes":30,"npd":0,"start_date":"Feb 26, 2026","days":31,"tags":[],"delta":0},{"id":809900021419065300,"post_url":"https://www.tumblr.com/blog/view/goodtransgirl/809900021419065344","type":"text","is_reblog":true,"added_content":false,"notes":187,"npd":0,"start_date":"Mar 1, 2026","days":28,"tags":[],"delta":0},{"id":809897367895752700,"post_url":"https://www.tumblr.com/blog/view/goodtransgirl/809897367895752704","type":"text","is_reblog":true,"added_content":false,"notes":2759,"npd":16.44,"start_date":"Feb 20, 2026","days":37,"tags":[],"delta":19},{"id":809893082434797600,"post_url":"https://www.tumblr.com/blog/view/goodtransgirl/809893082434797568","type":"text","is_reblog":true,"added_content":false,"notes":60,"npd":0,"start_date":"Mar 1, 2026","days":28,"tags":[],"delta":0},{"id":809888764431368200,"post_url":"https://www.tumblr.com/blog/view/goodtransgirl/809888764431368192","type":"text","is_reblog":true,"added_content":false,"notes":579,"npd":0,"start_date":"Feb 14, 2026","days":43,"tags":[],"delta":0},{"id":809884390716047400,"post_url":"https://www.tumblr.com/blog/view/goodtransgirl/809884390716047360","type":"text","is_reblog":true,"added_content":false,"notes":27453,"npd":1.73,"start_date":"Mar 8, 2024","days":751,"tags":[],"delta":2},{"id":809880122597441500,"post_url":"https://www.tumblr.com/blog/view/goodtransgirl/809880122597441536","type":"text","is_reblog":true,"added_content":false,"notes":15210,"npd":41.53,"start_date":"Feb 26, 2026","days":31,"tags":[],"delta":48},{"id":809875717306433500,"post_url":"https://www.tumblr.com/blog/view/goodtransgirl/809875717306433536","type":"text","is_reblog":true,"added_content":false,"notes":88410,"npd":318.43,"start_date":"Feb 16, 2026","days":41,"tags":[],"delta":368},{"id":809871438078181400,"post_url":"https://www.tumblr.com/blog/view/goodtransgirl/809871438078181376","type":"answer","is_reblog":true,"added_content":false,"notes":38,"npd":0,"start_date":"Mar 1, 2026","days":28,"tags":[],"delta":0},{"id":809867155709493200,"post_url":"https://www.tumblr.com/blog/view/goodtransgirl/809867155709493248","type":"text","is_reblog":true,"added_content":false,"notes":335,"npd":0,"start_date":"Jan 28, 2026","days":60,"tags":[],"delta":0},{"id":809862896989421600,"post_url":"https://www.tumblr.com/blog/view/goodtransgirl/809862896989421569","type":"text","is_reblog":true,"added_content":false,"notes":26,"npd":0,"start_date":"Mar 1, 2026","days":28,"tags":[],"delta":0},{"id":809854200430346200,"post_url":"https://www.tumblr.com/blog/view/goodtransgirl/809854200430346240","type":"text","is_reblog":true,"added_content":false,"notes":591,"npd":0,"start_date":"Feb 26, 2026","days":31,"tags":[],"delta":0},{"id":809849927254556700,"post_url":"https://www.tumblr.com/blog/view/goodtransgirl/809849927254556672","type":"text","is_reblog":true,"added_content":false,"notes":1585,"npd":1.73,"start_date":"Jan 21, 2026","days":67,"tags":[],"delta":2},{"id":809845516376686600,"post_url":"https://www.tumblr.com/blog/view/goodtransgirl/809845516376686592","type":"text","is_reblog":true,"added_content":false,"notes":123,"npd":0.87,"start_date":"Feb 28, 2026","days":29,"tags":[],"delta":1},{"id":809841241097404400,"post_url":"https://www.tumblr.com/blog/view/goodtransgirl/809841241097404417","type":"text","is_reblog":true,"added_content":false,"notes":24805,"npd":179.98,"start_date":"Feb 23, 2026","days":34,"tags":[],"delta":208}]}