{"exported_at":"2026-04-13T19:02:54.449Z","blog":"goodtransgirl.tumblr.com","page":2,"total_pages":6,"total_rows":1767,"posts":[{"id":"812615777217822720","post_url":"https://www.tumblr.com/blog/view/goodtransgirl/812615777217822720","notes":493,"npd":0.31,"is_reblog":true,"added_content":false,"tags":[],"delta":4},{"id":"812611498513924096","post_url":"https://www.tumblr.com/blog/view/goodtransgirl/812611498513924096","notes":818688,"npd":134.63,"is_reblog":true,"added_content":false,"tags":[],"delta":1728},{"id":"812607221337882624","post_url":"https://www.tumblr.com/blog/view/goodtransgirl/812607221337882624","notes":15424,"npd":16.52,"is_reblog":true,"added_content":false,"tags":[],"delta":212},{"id":"812603092223803392","post_url":"https://www.tumblr.com/blog/view/goodtransgirl/812603092223803392","notes":79947,"npd":413.86,"is_reblog":true,"added_content":false,"tags":[],"delta":5312},{"id":"812598537112174592","post_url":"https://www.tumblr.com/blog/view/goodtransgirl/812598537112174592","notes":269,"npd":0.31,"is_reblog":true,"added_content":false,"tags":[],"delta":4},{"id":"812594273265565696","post_url":"https://www.tumblr.com/blog/view/goodtransgirl/812594273265565696","notes":17366,"npd":463.87,"is_reblog":true,"added_content":false,"tags":[],"delta":5954,"likes":11280,"reblogs":3926,"comments":0},{"id":"812589856786087936","post_url":"https://www.tumblr.com/blog/view/goodtransgirl/812589856786087936","notes":36,"npd":0.22,"is_reblog":true,"added_content":false,"tags":[],"delta":3},{"id":"812585576752627712","post_url":"https://www.tumblr.com/blog/view/goodtransgirl/812585576752627712","notes":24,"npd":0.22,"is_reblog":true,"added_content":false,"tags":[],"delta":3},{"id":"812581307669495808","post_url":"https://www.tumblr.com/blog/view/goodtransgirl/812581307669495808","notes":7867,"npd":3.42,"is_reblog":true,"added_content":false,"tags":[],"delta":46},{"id":"812577022237900800","post_url":"https://www.tumblr.com/blog/view/goodtransgirl/812577022237900800","notes":146,"npd":3.05,"is_reblog":true,"added_content":false,"tags":[],"delta":41},{"id":"812568337002512384","post_url":"https://www.tumblr.com/blog/view/goodtransgirl/812568337002512384","notes":3904,"npd":0.37,"is_reblog":true,"added_content":false,"tags":[],"delta":5},{"id":"812564066976563200","post_url":"https://www.tumblr.com/blog/view/goodtransgirl/812564066976563200","notes":2496,"npd":0,"is_reblog":true,"added_content":false,"tags":[],"delta":0},{"id":"812559659484479488","post_url":"https://www.tumblr.com/blog/view/goodtransgirl/812559659484479488","notes":1358,"npd":26.35,"is_reblog":true,"added_content":false,"tags":[],"delta":354},{"id":"812555378309136385","post_url":"https://www.tumblr.com/blog/view/goodtransgirl/812555378309136385","notes":256984,"npd":50.57,"is_reblog":true,"added_content":false,"tags":[],"delta":697},{"id":"812551099958673408","post_url":"https://www.tumblr.com/blog/view/goodtransgirl/812551099958673408","notes":152,"npd":0.22,"is_reblog":true,"added_content":false,"tags":[],"delta":3},{"id":"812546826132766720","post_url":"https://www.tumblr.com/blog/view/goodtransgirl/812546826132766720","notes":10828,"npd":14.95,"is_reblog":true,"added_content":false,"tags":[],"delta":206},{"id":"812542663708590080","post_url":"https://www.tumblr.com/blog/view/goodtransgirl/812542663708590080","notes":70,"npd":0.58,"is_reblog":true,"added_content":false,"tags":[],"delta":8},{"id":"812538106988347392","post_url":"https://www.tumblr.com/blog/view/goodtransgirl/812538106988347392","notes":498,"npd":0.21,"is_reblog":true,"added_content":false,"tags":[],"delta":3},{"id":"812533869209354240","post_url":"https://www.tumblr.com/blog/view/goodtransgirl/812533869209354240","notes":105749,"npd":67.9,"is_reblog":true,"added_content":false,"tags":[],"delta":953},{"id":"812529466562740224","post_url":"https://www.tumblr.com/blog/view/goodtransgirl/812529466562740224","notes":86117,"npd":20.13,"is_reblog":true,"added_content":false,"tags":[],"delta":283},{"id":"812525190653313024","post_url":"https://www.tumblr.com/blog/view/goodtransgirl/812525190653313024","notes":5475,"npd":4.91,"is_reblog":true,"added_content":false,"tags":[],"delta":69},{"id":"812520908126388224","post_url":"https://www.tumblr.com/blog/view/goodtransgirl/812520908126388224","notes":121022,"npd":77.04,"is_reblog":true,"added_content":false,"tags":[],"delta":1083},{"id":"812516646165135360","post_url":"https://www.tumblr.com/blog/view/goodtransgirl/812516646165135360","notes":3290,"npd":8.32,"is_reblog":true,"added_content":false,"tags":[],"delta":117},{"id":"812512567792697344","post_url":"https://www.tumblr.com/blog/view/goodtransgirl/812512567792697344","notes":24221,"npd":248.47,"is_reblog":true,"added_content":false,"tags":[],"delta":3493},{"id":"812507938096922625","post_url":"https://www.tumblr.com/blog/view/goodtransgirl/812507938096922625","notes":78,"npd":1.95,"is_reblog":true,"added_content":false,"tags":[],"delta":28},{"id":"812503668452638720","post_url":"https://www.tumblr.com/blog/view/goodtransgirl/812503668452638720","notes":2908,"npd":3.89,"is_reblog":true,"added_content":false,"tags":[],"delta":56},{"id":"812499263710969856","post_url":"https://www.tumblr.com/blog/view/goodtransgirl/812499263710969856","notes":385,"npd":13.56,"is_reblog":true,"added_content":false,"tags":[],"delta":195},{"id":"812494988154929153","post_url":"https://www.tumblr.com/blog/view/goodtransgirl/812494988154929153","notes":12454,"npd":22.04,"is_reblog":true,"added_content":false,"tags":[],"delta":317},{"id":"812490706831785984","post_url":"https://www.tumblr.com/blog/view/goodtransgirl/812490706831785984","notes":34446,"npd":20.23,"is_reblog":true,"added_content":false,"tags":[],"delta":291},{"id":"812486309232918528","post_url":"https://www.tumblr.com/blog/view/goodtransgirl/812486309232918528","notes":3100,"npd":29.97,"is_reblog":true,"added_content":false,"tags":[],"delta":431},{"id":"812477739178344448","post_url":"https://www.tumblr.com/blog/view/goodtransgirl/812477739178344448","notes":188706,"npd":538.88,"is_reblog":true,"added_content":false,"tags":[],"delta":7899},{"id":"812473538028224512","post_url":"https://www.tumblr.com/blog/view/goodtransgirl/812473538028224512","notes":2547,"npd":3.47,"is_reblog":true,"added_content":false,"tags":[],"delta":51},{"id":"812469066641047552","post_url":"https://www.tumblr.com/blog/view/goodtransgirl/812469066641047552","notes":1291,"npd":0.2,"is_reblog":true,"added_content":false,"tags":[],"delta":3},{"id":"812464864942489600","post_url":"https://www.tumblr.com/blog/view/goodtransgirl/812464864942489600","notes":15040,"npd":37.41,"is_reblog":true,"added_content":false,"tags":[],"delta":554},{"id":"812460499223658496","post_url":"https://www.tumblr.com/blog/view/goodtransgirl/812460499223658496","notes":915,"npd":11.14,"is_reblog":true,"added_content":false,"tags":[],"delta":165},{"id":"812456236740149248","post_url":"https://www.tumblr.com/blog/view/goodtransgirl/812456236740149248","notes":967,"npd":8.05,"is_reblog":true,"added_content":false,"tags":[],"delta":120},{"id":"812452026037469185","post_url":"https://www.tumblr.com/blog/view/goodtransgirl/812452026037469185","notes":313,"npd":2.28,"is_reblog":true,"added_content":false,"tags":[],"delta":34},{"id":"812447544698355712","post_url":"https://www.tumblr.com/blog/view/goodtransgirl/812447544698355712","notes":623,"npd":21.87,"is_reblog":true,"added_content":false,"tags":[],"delta":326},{"id":"812443272996962304","post_url":"https://www.tumblr.com/blog/view/goodtransgirl/812443272996962304","notes":250,"npd":2.06,"is_reblog":true,"added_content":false,"tags":[],"delta":31},{"id":"812438888108982272","post_url":"https://www.tumblr.com/blog/view/goodtransgirl/812438888108982272","notes":993,"npd":1.06,"is_reblog":true,"added_content":false,"tags":[],"delta":16},{"id":"812434654438277120","post_url":"https://www.tumblr.com/blog/view/goodtransgirl/812434654438277120","notes":3899,"npd":9.12,"is_reblog":true,"added_content":false,"tags":["it me","oh look it me"],"delta":138},{"id":"812430328643944448","post_url":"https://www.tumblr.com/blog/view/goodtransgirl/812430328643944448","notes":1735,"npd":0.79,"is_reblog":true,"added_content":false,"tags":[],"delta":12},{"id":"812426023436222464","post_url":"https://www.tumblr.com/blog/view/goodtransgirl/812426023436222464","notes":5205,"npd":245.99,"is_reblog":true,"added_content":false,"tags":[],"delta":3736,"likes":2497,"reblogs":1671,"comments":0},{"id":"812421913741787136","post_url":"https://www.tumblr.com/blog/view/goodtransgirl/812421913741787136","notes":4014,"npd":218.55,"is_reblog":true,"added_content":false,"tags":[],"delta":3336},{"id":"812417352812707840","post_url":"https://www.tumblr.com/blog/view/goodtransgirl/812417352812707840","notes":161245,"npd":39.77,"is_reblog":true,"added_content":false,"tags":[],"delta":607},{"id":"812413064382169088","post_url":"https://www.tumblr.com/blog/view/goodtransgirl/812413064382169088","notes":104,"npd":0.59,"is_reblog":true,"added_content":false,"tags":[],"delta":9},{"id":"812408660853768192","post_url":"https://www.tumblr.com/blog/view/goodtransgirl/812408660853768192","notes":1289,"npd":37.72,"is_reblog":true,"added_content":false,"tags":[],"delta":581},{"id":"812404381538451456","post_url":"https://www.tumblr.com/blog/view/goodtransgirl/812404381538451456","notes":475,"npd":1.49,"is_reblog":true,"added_content":false,"tags":[],"delta":23},{"id":"812400110607712256","post_url":"https://www.tumblr.com/blog/view/goodtransgirl/812400110607712256","notes":898,"npd":5.37,"is_reblog":true,"added_content":false,"tags":[],"delta":83},{"id":"812395859986776064","post_url":"https://www.tumblr.com/blog/view/goodtransgirl/812395859986776064","notes":45,"npd":0.71,"is_reblog":true,"added_content":false,"tags":[],"delta":11},{"id":"812387148736184320","post_url":"https://www.tumblr.com/blog/view/goodtransgirl/812387148736184320","notes":804,"npd":0.32,"is_reblog":true,"added_content":false,"tags":[],"delta":5},{"id":"812382871325163520","post_url":"https://www.tumblr.com/blog/view/goodtransgirl/812382871325163520","notes":1303925,"npd":148.13,"is_reblog":true,"added_content":false,"tags":[],"delta":2289},{"id":"812382310083280896","post_url":"https://www.tumblr.com/blog/view/goodtransgirl/812382310083280896","notes":61,"npd":1.81,"is_reblog":true,"added_content":false,"tags":[],"delta":28},{"id":"812382190419820544","post_url":"https://www.tumblr.com/blog/view/goodtransgirl/812382190419820544","notes":93,"npd":0.19,"is_reblog":true,"added_content":false,"tags":[],"delta":3},{"id":"812378464790495232","post_url":"https://www.tumblr.com/blog/view/goodtransgirl/812378464790495232","notes":902,"npd":40.32,"is_reblog":true,"added_content":false,"tags":[],"delta":623},{"id":"812374200773935104","post_url":"https://www.tumblr.com/blog/view/goodtransgirl/812374200773935104","notes":36183,"npd":36.3,"is_reblog":true,"added_content":false,"tags":[],"delta":561},{"id":"812369901356482560","post_url":"https://www.tumblr.com/blog/view/goodtransgirl/812369901356482560","notes":1493,"npd":3.3,"is_reblog":true,"added_content":false,"tags":[],"delta":51},{"id":"812361392023846912","post_url":"https://www.tumblr.com/blog/view/goodtransgirl/812361392023846912","notes":107337,"npd":65.01,"is_reblog":true,"added_content":false,"tags":[],"delta":1035},{"id":"812356953611386881","post_url":"https://www.tumblr.com/blog/view/goodtransgirl/812356953611386881","notes":14617,"npd":130.34,"is_reblog":true,"added_content":false,"tags":[],"delta":2075},{"id":"812352662405316608","post_url":"https://www.tumblr.com/blog/view/goodtransgirl/812352662405316608","notes":12,"npd":0.31,"is_reblog":true,"added_content":false,"tags":[],"delta":5},{"id":"812348266254663680","post_url":"https://www.tumblr.com/blog/view/goodtransgirl/812348266254663680","notes":678,"npd":5.28,"is_reblog":true,"added_content":false,"tags":[],"delta":85},{"id":"812344011006296066","post_url":"https://www.tumblr.com/blog/view/goodtransgirl/812344011006296066","notes":223,"npd":1.36,"is_reblog":true,"added_content":false,"tags":[],"delta":22},{"id":"812339716995284992","post_url":"https://www.tumblr.com/blog/view/goodtransgirl/812339716995284992","notes":1522,"npd":6.3,"is_reblog":true,"added_content":false,"tags":[],"delta":102},{"id":"812331535403532288","post_url":"https://www.tumblr.com/blog/view/goodtransgirl/812331535403532288","notes":3622,"npd":1.36,"is_reblog":true,"added_content":false,"tags":[],"delta":22},{"id":"812326690887008256","post_url":"https://www.tumblr.com/blog/view/goodtransgirl/812326690887008256","notes":32920,"npd":146.75,"is_reblog":true,"added_content":false,"tags":[],"delta":2381},{"id":"812322458262765568","post_url":"https://www.tumblr.com/blog/view/goodtransgirl/812322458262765568","notes":3240,"npd":5.86,"is_reblog":true,"added_content":false,"tags":[],"delta":95},{"id":"812318097242456064","post_url":"https://www.tumblr.com/blog/view/goodtransgirl/812318097242456064","notes":16952,"npd":296.33,"is_reblog":true,"added_content":false,"tags":[],"delta":4808},{"id":"812313799536361472","post_url":"https://www.tumblr.com/blog/view/goodtransgirl/812313799536361472","notes":9419,"npd":98.55,"is_reblog":true,"added_content":false,"tags":[],"delta":1599},{"id":"812309504237666304","post_url":"https://www.tumblr.com/blog/view/goodtransgirl/812309504237666304","notes":401,"npd":0.37,"is_reblog":true,"added_content":false,"tags":[],"delta":6},{"id":"812305237807366144","post_url":"https://www.tumblr.com/blog/view/goodtransgirl/812305237807366144","notes":2161,"npd":37.66,"is_reblog":true,"added_content":false,"tags":[],"delta":611},{"id":"812296548954324993","post_url":"https://www.tumblr.com/blog/view/goodtransgirl/812296548954324993","notes":1390,"npd":0.55,"is_reblog":true,"added_content":false,"tags":[],"delta":9},{"id":"812292265770926080","post_url":"https://www.tumblr.com/blog/view/goodtransgirl/812292265770926080","notes":23,"npd":0,"is_reblog":true,"added_content":false,"tags":[],"delta":0},{"id":"812287961961988096","post_url":"https://www.tumblr.com/blog/view/goodtransgirl/812287961961988096","notes":13,"npd":0.25,"is_reblog":true,"added_content":false,"tags":[],"delta":4},{"id":"812283577072074752","post_url":"https://www.tumblr.com/blog/view/goodtransgirl/812283577072074752","notes":7206,"npd":44.25,"is_reblog":true,"added_content":false,"tags":[],"delta":718},{"id":"812279234999533568","post_url":"https://www.tumblr.com/blog/view/goodtransgirl/812279234999533568","notes":1698,"npd":64.1,"is_reblog":true,"added_content":false,"tags":[],"delta":1040},{"id":"812270784514048000","post_url":"https://www.tumblr.com/blog/view/goodtransgirl/812270784514048000","notes":4028,"npd":39.57,"is_reblog":true,"added_content":false,"tags":[],"delta":642},{"id":"812266344864186368","post_url":"https://www.tumblr.com/blog/view/goodtransgirl/812266344864186368","notes":200,"npd":6.29,"is_reblog":true,"added_content":false,"tags":[],"delta":102},{"id":"812264963281502208","post_url":"https://www.tumblr.com/blog/view/goodtransgirl/812264963281502208","notes":1721,"npd":81.35,"is_reblog":true,"added_content":false,"tags":[],"delta":1320},{"id":"812262067028525056","post_url":"https://www.tumblr.com/blog/view/goodtransgirl/812262067028525056","notes":588591,"npd":47.7,"is_reblog":true,"added_content":false,"tags":[],"delta":774},{"id":"812257664708018176","post_url":"https://www.tumblr.com/blog/view/goodtransgirl/812257664708018176","notes":410,"npd":0.37,"is_reblog":true,"added_content":false,"tags":[],"delta":6},{"id":"812251789742292992","post_url":"https://www.tumblr.com/blog/view/goodtransgirl/812251789742292992","notes":196,"npd":0.55,"is_reblog":true,"added_content":false,"tags":[],"delta":9},{"id":"812249113902137344","post_url":"https://www.tumblr.com/blog/view/goodtransgirl/812249113902137344","notes":54671,"npd":89.74,"is_reblog":true,"added_content":false,"tags":[],"delta":1456},{"id":"812244859917402112","post_url":"https://www.tumblr.com/blog/view/goodtransgirl/812244859917402112","notes":6904,"npd":4.44,"is_reblog":true,"added_content":false,"tags":[],"delta":72},{"id":"812240658541789184","post_url":"https://www.tumblr.com/blog/view/goodtransgirl/812240658541789184","notes":6599,"npd":93.68,"is_reblog":true,"added_content":false,"tags":["it me","oh look it me","and usually overexplaining leads to misunderstanding as well tbh"],"delta":1520},{"id":"812236155768750080","post_url":"https://www.tumblr.com/blog/view/goodtransgirl/812236155768750080","notes":9550,"npd":73.22,"is_reblog":true,"added_content":false,"tags":[],"delta":1188},{"id":"812231864921276416","post_url":"https://www.tumblr.com/blog/view/goodtransgirl/812231864921276416","notes":5176,"npd":57.13,"is_reblog":true,"added_content":false,"tags":[],"delta":927},{"id":"812227473085546496","post_url":"https://www.tumblr.com/blog/view/goodtransgirl/812227473085546496","notes":667,"npd":9.24,"is_reblog":true,"added_content":false,"tags":[],"delta":150},{"id":"812223192099962880","post_url":"https://www.tumblr.com/blog/view/goodtransgirl/812223192099962880","notes":836,"npd":2.65,"is_reblog":true,"added_content":false,"tags":[],"delta":43},{"id":"812218836568899584","post_url":"https://www.tumblr.com/blog/view/goodtransgirl/812218836568899584","notes":80,"npd":4.07,"is_reblog":true,"added_content":false,"tags":[],"delta":66},{"id":"812214633550217216","post_url":"https://www.tumblr.com/blog/view/goodtransgirl/812214633550217216","notes":4109,"npd":33.65,"is_reblog":true,"added_content":false,"tags":[],"delta":546},{"id":"812205950531502080","post_url":"https://www.tumblr.com/blog/view/goodtransgirl/812205950531502080","notes":7,"npd":0,"is_reblog":true,"added_content":false,"tags":[],"delta":0},{"id":"812201684547878912","post_url":"https://www.tumblr.com/blog/view/goodtransgirl/812201684547878912","notes":24,"npd":0.06,"is_reblog":true,"added_content":false,"tags":[],"delta":1},{"id":"812197309987340288","post_url":"https://www.tumblr.com/blog/view/goodtransgirl/812197309987340288","notes":920,"npd":7.09,"is_reblog":true,"added_content":false,"tags":[],"delta":115},{"id":"812192985260474368","post_url":"https://www.tumblr.com/blog/view/goodtransgirl/812192985260474368","notes":1575,"npd":24.04,"is_reblog":true,"added_content":false,"tags":[],"delta":390},{"id":"812189800461467648","post_url":"https://www.tumblr.com/blog/view/goodtransgirl/812189800461467648","notes":2983,"npd":80.49,"is_reblog":true,"added_content":false,"tags":[],"delta":1306},{"id":"812188740143464448","post_url":"https://www.tumblr.com/blog/view/goodtransgirl/812188740143464448","notes":54,"npd":0.37,"is_reblog":true,"added_content":false,"tags":[],"delta":6},{"id":"812180183096393728","post_url":"https://www.tumblr.com/blog/view/goodtransgirl/812180183096393728","notes":164,"npd":0.12,"is_reblog":true,"added_content":false,"tags":[],"delta":2},{"id":"812171465946497024","post_url":"https://www.tumblr.com/blog/view/goodtransgirl/812171465946497024","notes":708,"npd":3.88,"is_reblog":true,"added_content":false,"tags":[],"delta":63},{"id":"812167068321529856","post_url":"https://www.tumblr.com/blog/view/goodtransgirl/812167068321529856","notes":546,"npd":4.07,"is_reblog":true,"added_content":false,"tags":[],"delta":66},{"id":"812164227044376576","post_url":"https://www.tumblr.com/blog/view/goodtransgirl/812164227044376576","notes":173,"npd":4.99,"is_reblog":true,"added_content":false,"tags":[],"delta":81},{"id":"812162788212490240","post_url":"https://www.tumblr.com/blog/view/goodtransgirl/812162788212490240","notes":122,"npd":0.25,"is_reblog":true,"added_content":false,"tags":[],"delta":4},{"id":"812161186868133888","post_url":"https://www.tumblr.com/blog/view/goodtransgirl/812161186868133888","notes":196,"npd":0.55,"is_reblog":true,"added_content":false,"tags":[],"delta":9},{"id":"812158501848793088","post_url":"https://www.tumblr.com/blog/view/goodtransgirl/812158501848793088","notes":285,"npd":0.55,"is_reblog":true,"added_content":false,"tags":[],"delta":9},{"id":"812154268796764160","post_url":"https://www.tumblr.com/blog/view/goodtransgirl/812154268796764160","notes":854,"npd":13,"is_reblog":true,"added_content":false,"tags":[],"delta":211},{"id":"812150108878733312","post_url":"https://www.tumblr.com/blog/view/goodtransgirl/812150108878733312","notes":1153,"npd":0.55,"is_reblog":true,"added_content":false,"tags":[],"delta":9},{"id":"812141269462728704","post_url":"https://www.tumblr.com/blog/view/goodtransgirl/812141269462728704","notes":2131,"npd":12.57,"is_reblog":true,"added_content":false,"tags":[],"delta":204},{"id":"812136873104474112","post_url":"https://www.tumblr.com/blog/view/goodtransgirl/812136873104474112","notes":18312,"npd":332.01,"is_reblog":true,"added_content":false,"tags":[],"delta":5387,"likes":9666,"reblogs":6958,"comments":0},{"id":"812132609396277248","post_url":"https://www.tumblr.com/blog/view/goodtransgirl/812132609396277248","notes":175,"npd":0,"is_reblog":true,"added_content":false,"tags":[],"delta":0},{"id":"812124072622407680","post_url":"https://www.tumblr.com/blog/view/goodtransgirl/812124072622407680","notes":805,"npd":0.18,"is_reblog":true,"added_content":false,"tags":[],"delta":3},{"id":"812115345703862272","post_url":"https://www.tumblr.com/blog/view/goodtransgirl/812115345703862272","notes":16304,"npd":3.02,"is_reblog":true,"added_content":false,"tags":[],"delta":49},{"id":"812112569909362688","post_url":"https://www.tumblr.com/blog/view/goodtransgirl/812112569909362688","notes":6,"npd":0.06,"is_reblog":true,"added_content":false,"tags":[],"delta":1},{"id":"812106709024849920","post_url":"https://www.tumblr.com/blog/view/goodtransgirl/812106709024849920","notes":216,"npd":0.06,"is_reblog":true,"added_content":false,"tags":["🥺🥺🥺","🥺👉👈"],"delta":1},{"id":"812102423775789056","post_url":"https://www.tumblr.com/blog/view/goodtransgirl/812102423775789056","notes":226,"npd":0.06,"is_reblog":true,"added_content":false,"tags":[],"delta":1},{"id":"812093847882645504","post_url":"https://www.tumblr.com/blog/view/goodtransgirl/812093847882645504","notes":576,"npd":3.88,"is_reblog":true,"added_content":false,"tags":["i am so gay","omg im so gay"],"delta":63},{"id":"812089602834890752","post_url":"https://www.tumblr.com/blog/view/goodtransgirl/812089602834890752","notes":91,"npd":0,"is_reblog":true,"added_content":false,"tags":[],"delta":0},{"id":"812085193229893632","post_url":"https://www.tumblr.com/blog/view/goodtransgirl/812085193229893632","notes":71,"npd":0.18,"is_reblog":true,"added_content":false,"tags":[],"delta":3},{"id":"812083897079906305","post_url":"https://www.tumblr.com/blog/view/goodtransgirl/812083897079906305","notes":68,"npd":0.68,"is_reblog":true,"added_content":false,"tags":[],"delta":11},{"id":"812080882692259840","post_url":"https://www.tumblr.com/blog/view/goodtransgirl/812080882692259840","notes":608,"npd":0.25,"is_reblog":true,"added_content":false,"tags":[],"delta":4},{"id":"812076482830680064","post_url":"https://www.tumblr.com/blog/view/goodtransgirl/812076482830680064","notes":95104,"npd":30.82,"is_reblog":true,"added_content":false,"tags":[],"delta":500},{"id":"812070629241176064","post_url":"https://www.tumblr.com/blog/view/goodtransgirl/812070629241176064","notes":196,"npd":0.55,"is_reblog":true,"added_content":false,"tags":[],"delta":9},{"id":"812063660587565056","post_url":"https://www.tumblr.com/blog/view/goodtransgirl/812063660587565056","notes":169,"npd":0.74,"is_reblog":true,"added_content":false,"tags":[],"delta":12},{"id":"812059754760437760","post_url":"https://www.tumblr.com/blog/view/goodtransgirl/812059754760437760","notes":219081,"npd":0.06,"is_reblog":true,"added_content":false,"tags":["shitposting","shitpost","meme","memes","retro meme","retro memes","tumblr classic","trans blog","transgender","sapphic","wlw","lgbtq","gay","mtf","transbian","lgbtqia","sapphic blog"],"delta":1},{"id":"812054954078601216","post_url":"https://www.tumblr.com/blog/view/goodtransgirl/812054954078601216","notes":4688,"npd":141.94,"is_reblog":true,"added_content":false,"tags":[],"delta":2303},{"id":"812053047988666368","post_url":"https://www.tumblr.com/blog/view/goodtransgirl/812053047988666368","notes":4692,"npd":14.05,"is_reblog":true,"added_content":false,"tags":[],"delta":228},{"id":"812052122105446401","post_url":"https://www.tumblr.com/blog/view/goodtransgirl/812052122105446401","notes":4137,"npd":14.55,"is_reblog":true,"added_content":false,"tags":[],"delta":236},{"id":"812051806384472064","post_url":"https://www.tumblr.com/blog/view/goodtransgirl/812051806384472064","notes":2715,"npd":0.74,"is_reblog":true,"added_content":false,"tags":[],"delta":12},{"id":"812050671354494976","post_url":"https://www.tumblr.com/blog/view/goodtransgirl/812050671354494976","notes":14888,"npd":202.4,"is_reblog":true,"added_content":false,"tags":[],"delta":3284,"likes":10612,"reblogs":3553,"comments":0},{"id":"812046275018194944","post_url":"https://www.tumblr.com/blog/view/goodtransgirl/812046275018194944","notes":46483,"npd":21.45,"is_reblog":true,"added_content":false,"tags":[],"delta":348},{"id":"812042016846430208","post_url":"https://www.tumblr.com/blog/view/goodtransgirl/812042016846430208","notes":9623,"npd":105.02,"is_reblog":true,"added_content":false,"tags":[],"delta":1704},{"id":"812037709967294464","post_url":"https://www.tumblr.com/blog/view/goodtransgirl/812037709967294464","notes":1006,"npd":17.87,"is_reblog":true,"added_content":false,"tags":[],"delta":290},{"id":"812033332218150912","post_url":"https://www.tumblr.com/blog/view/goodtransgirl/812033332218150912","notes":1368,"npd":2.03,"is_reblog":true,"added_content":false,"tags":[],"delta":33},{"id":"812020476110127104","post_url":"https://www.tumblr.com/blog/view/goodtransgirl/812020476110127104","notes":1452,"npd":6.04,"is_reblog":true,"added_content":false,"tags":[],"delta":98},{"id":"812016072973762561","post_url":"https://www.tumblr.com/blog/view/goodtransgirl/812016072973762561","notes":74218,"npd":107.86,"is_reblog":true,"added_content":false,"tags":[],"delta":1750},{"id":"812011813242830848","post_url":"https://www.tumblr.com/blog/view/goodtransgirl/812011813242830848","notes":1351,"npd":7.83,"is_reblog":true,"added_content":false,"tags":[],"delta":127},{"id":"812007577430949889","post_url":"https://www.tumblr.com/blog/view/goodtransgirl/812007577430949889","notes":2118,"npd":40.37,"is_reblog":true,"added_content":false,"tags":[],"delta":655},{"id":"812003137970946048","post_url":"https://www.tumblr.com/blog/view/goodtransgirl/812003137970946048","notes":234,"npd":0.74,"is_reblog":true,"added_content":false,"tags":[],"delta":12},{"id":"811999125891612672","post_url":"https://www.tumblr.com/blog/view/goodtransgirl/811999125891612672","notes":9285,"npd":8.14,"is_reblog":true,"added_content":false,"tags":[],"delta":132},{"id":"811994565264424960","post_url":"https://www.tumblr.com/blog/view/goodtransgirl/811994565264424960","notes":23467,"npd":1.91,"is_reblog":true,"added_content":false,"tags":[],"delta":31},{"id":"811990289756635136","post_url":"https://www.tumblr.com/blog/view/goodtransgirl/811990289756635136","notes":3157,"npd":14.61,"is_reblog":true,"added_content":false,"tags":[],"delta":237},{"id":"811985884047163392","post_url":"https://www.tumblr.com/blog/view/goodtransgirl/811985884047163392","notes":279595,"npd":121.17,"is_reblog":true,"added_content":false,"tags":[],"delta":1966},{"id":"811981594154942464","post_url":"https://www.tumblr.com/blog/view/goodtransgirl/811981594154942464","notes":30868,"npd":437.71,"is_reblog":true,"added_content":false,"tags":[],"delta":7102,"likes":18808,"reblogs":11267,"comments":0},{"id":"811977324675350528","post_url":"https://www.tumblr.com/blog/view/goodtransgirl/811977324675350528","notes":1066,"npd":4.81,"is_reblog":true,"added_content":false,"tags":[],"delta":78},{"id":"811973046883729408","post_url":"https://www.tumblr.com/blog/view/goodtransgirl/811973046883729408","notes":442,"npd":7.52,"is_reblog":true,"added_content":false,"tags":[],"delta":122},{"id":"811968970185949184","post_url":"https://www.tumblr.com/blog/view/goodtransgirl/811968970185949184","notes":4677,"npd":9.37,"is_reblog":true,"added_content":false,"tags":[],"delta":152},{"id":"811964355493199873","post_url":"https://www.tumblr.com/blog/view/goodtransgirl/811964355493199873","notes":60,"npd":0.06,"is_reblog":true,"added_content":false,"tags":[],"delta":1},{"id":"811960069809930241","post_url":"https://www.tumblr.com/blog/view/goodtransgirl/811960069809930241","notes":24819,"npd":12.63,"is_reblog":true,"added_content":false,"tags":[],"delta":205},{"id":"811955802742161408","post_url":"https://www.tumblr.com/blog/view/goodtransgirl/811955802742161408","notes":62537,"npd":7.46,"is_reblog":true,"added_content":false,"tags":[],"delta":121},{"id":"811934158224064512","post_url":"https://www.tumblr.com/blog/view/goodtransgirl/811934158224064512","notes":13992,"npd":0.62,"is_reblog":true,"added_content":false,"tags":["it me","omg its me"],"delta":10},{"id":"811929902020444160","post_url":"https://www.tumblr.com/blog/view/goodtransgirl/811929902020444160","notes":440,"npd":0.37,"is_reblog":true,"added_content":false,"tags":[],"delta":6},{"id":"811925515007148032","post_url":"https://www.tumblr.com/blog/view/goodtransgirl/811925515007148032","notes":5742,"npd":9.92,"is_reblog":true,"added_content":false,"tags":[],"delta":161},{"id":"811921205577826304","post_url":"https://www.tumblr.com/blog/view/goodtransgirl/811921205577826304","notes":4642,"npd":83.7,"is_reblog":true,"added_content":false,"tags":[],"delta":1358},{"id":"811916851525320704","post_url":"https://www.tumblr.com/blog/view/goodtransgirl/811916851525320704","notes":2754,"npd":44.25,"is_reblog":true,"added_content":false,"tags":[],"delta":718},{"id":"811911168829669377","post_url":"https://www.tumblr.com/blog/view/goodtransgirl/811911168829669377","notes":118,"npd":0.12,"is_reblog":true,"added_content":false,"tags":[],"delta":2},{"id":"811908603874279424","post_url":"https://www.tumblr.com/blog/view/goodtransgirl/811908603874279424","notes":19,"npd":0.06,"is_reblog":true,"added_content":false,"tags":[],"delta":1},{"id":"811899615124373504","post_url":"https://www.tumblr.com/blog/view/goodtransgirl/811899615124373504","notes":4352,"npd":0.12,"is_reblog":true,"added_content":false,"tags":[],"delta":2},{"id":"811895317480013824","post_url":"https://www.tumblr.com/blog/view/goodtransgirl/811895317480013824","notes":283,"npd":1.48,"is_reblog":true,"added_content":false,"tags":[],"delta":24},{"id":"811890995629342720","post_url":"https://www.tumblr.com/blog/view/goodtransgirl/811890995629342720","notes":232022,"npd":115.99,"is_reblog":true,"added_content":false,"tags":[],"delta":1882},{"id":"811886731055022080","post_url":"https://www.tumblr.com/blog/view/goodtransgirl/811886731055022080","notes":7206,"npd":44.25,"is_reblog":true,"added_content":false,"tags":[],"delta":718},{"id":"811882444460572672","post_url":"https://www.tumblr.com/blog/view/goodtransgirl/811882444460572672","notes":617,"npd":2.84,"is_reblog":true,"added_content":false,"tags":[],"delta":46},{"id":"811878272794296320","post_url":"https://www.tumblr.com/blog/view/goodtransgirl/811878272794296320","notes":31,"npd":0.06,"is_reblog":true,"added_content":false,"tags":[],"delta":1},{"id":"811873761594867712","post_url":"https://www.tumblr.com/blog/view/goodtransgirl/811873761594867712","notes":15,"npd":0,"is_reblog":true,"added_content":false,"tags":[],"delta":0},{"id":"811869478915899392","post_url":"https://www.tumblr.com/blog/view/goodtransgirl/811869478915899392","notes":76964,"npd":67.18,"is_reblog":true,"added_content":false,"tags":[],"delta":1090},{"id":"811865086070243328","post_url":"https://www.tumblr.com/blog/view/goodtransgirl/811865086070243328","notes":44,"npd":0,"is_reblog":true,"added_content":false,"tags":[],"delta":0},{"id":"811860794094632960","post_url":"https://www.tumblr.com/blog/view/goodtransgirl/811860794094632960","notes":602,"npd":3.94,"is_reblog":true,"added_content":false,"tags":[],"delta":64},{"id":"811856528144465920","post_url":"https://www.tumblr.com/blog/view/goodtransgirl/811856528144465920","notes":177946,"npd":59.17,"is_reblog":true,"added_content":false,"tags":[],"delta":960},{"id":"811852268115755008","post_url":"https://www.tumblr.com/blog/view/goodtransgirl/811852268115755008","notes":9456,"npd":24.1,"is_reblog":true,"added_content":false,"tags":[],"delta":391},{"id":"811843559946960896","post_url":"https://www.tumblr.com/blog/view/goodtransgirl/811843559946960896","notes":135,"npd":0.55,"is_reblog":true,"added_content":false,"tags":[],"delta":9},{"id":"811839287113007104","post_url":"https://www.tumblr.com/blog/view/goodtransgirl/811839287113007104","notes":2032,"npd":10.05,"is_reblog":true,"added_content":false,"tags":[],"delta":163},{"id":"811834898766856192","post_url":"https://www.tumblr.com/blog/view/goodtransgirl/811834898766856192","notes":4840,"npd":36.05,"is_reblog":true,"added_content":false,"tags":[],"delta":585},{"id":"811830602353508352","post_url":"https://www.tumblr.com/blog/view/goodtransgirl/811830602353508352","notes":11562,"npd":3.82,"is_reblog":true,"added_content":false,"tags":["it me","oh look it me"],"delta":62},{"id":"811826323401113600","post_url":"https://www.tumblr.com/blog/view/goodtransgirl/811826323401113600","notes":3870,"npd":1.05,"is_reblog":true,"added_content":false,"tags":[],"delta":17},{"id":"811822046002708480","post_url":"https://www.tumblr.com/blog/view/goodtransgirl/811822046002708480","notes":403,"npd":0,"is_reblog":true,"added_content":false,"tags":[],"delta":0},{"id":"811817902354333696","post_url":"https://www.tumblr.com/blog/view/goodtransgirl/811817902354333696","notes":718,"npd":3.76,"is_reblog":true,"added_content":false,"tags":[],"delta":61},{"id":"811813364996161536","post_url":"https://www.tumblr.com/blog/view/goodtransgirl/811813364996161536","notes":438,"npd":0.12,"is_reblog":true,"added_content":false,"tags":[],"delta":2},{"id":"811809085769089025","post_url":"https://www.tumblr.com/blog/view/goodtransgirl/811809085769089025","notes":34185,"npd":0.99,"is_reblog":true,"added_content":false,"tags":["shitposting","shitpost","meme","memes","retro meme","retro memes","tumblr classic","trans blog","transgender","sapphic","wlw","lgbtq","gay","mtf","transbian","lgbtqia","sapphic blog"],"delta":16},{"id":"811804701955915776","post_url":"https://www.tumblr.com/blog/view/goodtransgirl/811804701955915776","notes":90,"npd":0,"is_reblog":true,"added_content":false,"tags":[],"delta":0},{"id":"811800421122424832","post_url":"https://www.tumblr.com/blog/view/goodtransgirl/811800421122424832","notes":417,"npd":0.92,"is_reblog":true,"added_content":false,"tags":[],"delta":15},{"id":"811798798203486208","post_url":"https://www.tumblr.com/blog/view/goodtransgirl/811798798203486208","notes":196,"npd":0.55,"is_reblog":true,"added_content":false,"tags":[],"delta":9},{"id":"811796125653843968","post_url":"https://www.tumblr.com/blog/view/goodtransgirl/811796125653843968","notes":41,"npd":0.12,"is_reblog":true,"added_content":false,"tags":[],"delta":2},{"id":"811791854975811584","post_url":"https://www.tumblr.com/blog/view/goodtransgirl/811791854975811584","notes":14093,"npd":40.68,"is_reblog":true,"added_content":false,"tags":[],"delta":660},{"id":"811787968962576385","post_url":"https://www.tumblr.com/blog/view/goodtransgirl/811787968962576385","notes":1204,"npd":7.4,"is_reblog":true,"added_content":false,"tags":[],"delta":120},{"id":"811783167950422016","post_url":"https://www.tumblr.com/blog/view/goodtransgirl/811783167950422016","notes":7,"npd":0.18,"is_reblog":true,"added_content":false,"tags":[],"delta":3},{"id":"811778881237499904","post_url":"https://www.tumblr.com/blog/view/goodtransgirl/811778881237499904","notes":1969,"npd":24.59,"is_reblog":true,"added_content":false,"tags":[],"delta":399},{"id":"811774476895371264","post_url":"https://www.tumblr.com/blog/view/goodtransgirl/811774476895371264","notes":371,"npd":0.18,"is_reblog":true,"added_content":false,"tags":[],"delta":3},{"id":"811770208757972992","post_url":"https://www.tumblr.com/blog/view/goodtransgirl/811770208757972992","notes":5063,"npd":6.47,"is_reblog":true,"added_content":false,"tags":[],"delta":105},{"id":"811761549947682816","post_url":"https://www.tumblr.com/blog/view/goodtransgirl/811761549947682816","notes":2440,"npd":3.57,"is_reblog":true,"added_content":false,"tags":[],"delta":58},{"id":"811752962397519872","post_url":"https://www.tumblr.com/blog/view/goodtransgirl/811752962397519872","notes":12041,"npd":25.95,"is_reblog":true,"added_content":false,"tags":[],"delta":421},{"id":"811748687439151104","post_url":"https://www.tumblr.com/blog/view/goodtransgirl/811748687439151104","notes":250583,"npd":61.02,"is_reblog":true,"added_content":false,"tags":[],"delta":990},{"id":"811744407954030592","post_url":"https://www.tumblr.com/blog/view/goodtransgirl/811744407954030592","notes":532,"npd":10.54,"is_reblog":true,"added_content":false,"tags":[],"delta":171},{"id":"811740012801605634","post_url":"https://www.tumblr.com/blog/view/goodtransgirl/811740012801605634","notes":2911,"npd":8.51,"is_reblog":true,"added_content":false,"tags":[],"delta":138},{"id":"811735725274955776","post_url":"https://www.tumblr.com/blog/view/goodtransgirl/811735725274955776","notes":2695,"npd":31,"is_reblog":true,"added_content":false,"tags":[],"delta":503},{"id":"811731447127949312","post_url":"https://www.tumblr.com/blog/view/goodtransgirl/811731447127949312","notes":1496,"npd":6.96,"is_reblog":true,"added_content":false,"tags":[],"delta":113},{"id":"811722822044057600","post_url":"https://www.tumblr.com/blog/view/goodtransgirl/811722822044057600","notes":1378,"npd":14.61,"is_reblog":true,"added_content":false,"tags":[],"delta":237},{"id":"811718508502204416","post_url":"https://www.tumblr.com/blog/view/goodtransgirl/811718508502204416","notes":97299,"npd":12.45,"is_reblog":true,"added_content":false,"tags":[],"delta":202},{"id":"811714099693158400","post_url":"https://www.tumblr.com/blog/view/goodtransgirl/811714099693158400","notes":34,"npd":0,"is_reblog":true,"added_content":false,"tags":[],"delta":0},{"id":"811710844305096704","post_url":"https://www.tumblr.com/blog/view/goodtransgirl/811710844305096704","notes":11,"npd":0,"is_reblog":true,"added_content":false,"tags":[],"delta":0},{"id":"811709844392443904","post_url":"https://www.tumblr.com/blog/view/goodtransgirl/811709844392443904","notes":2262,"npd":40.06,"is_reblog":true,"added_content":false,"tags":[],"delta":650},{"id":"811708237570244608","post_url":"https://www.tumblr.com/blog/view/goodtransgirl/811708237570244608","notes":196,"npd":0.55,"is_reblog":true,"added_content":false,"tags":[],"delta":9},{"id":"811705536983744512","post_url":"https://www.tumblr.com/blog/view/goodtransgirl/811705536983744512","notes":2145,"npd":23.91,"is_reblog":true,"added_content":false,"tags":[],"delta":388},{"id":"811701255524220928","post_url":"https://www.tumblr.com/blog/view/goodtransgirl/811701255524220928","notes":5144,"npd":35.75,"is_reblog":true,"added_content":false,"tags":[],"delta":580},{"id":"811697116322889728","post_url":"https://www.tumblr.com/blog/view/goodtransgirl/811697116322889728","notes":43502,"npd":51.09,"is_reblog":true,"added_content":false,"tags":[],"delta":829},{"id":"811692564387364865","post_url":"https://www.tumblr.com/blog/view/goodtransgirl/811692564387364865","notes":1983,"npd":37.04,"is_reblog":true,"added_content":false,"tags":[],"delta":601},{"id":"811683885533544448","post_url":"https://www.tumblr.com/blog/view/goodtransgirl/811683885533544448","notes":17464,"npd":35.75,"is_reblog":true,"added_content":false,"tags":[],"delta":580},{"id":"811679599473868800","post_url":"https://www.tumblr.com/blog/view/goodtransgirl/811679599473868800","notes":179,"npd":2.1,"is_reblog":true,"added_content":false,"tags":[],"delta":34},{"id":"811675332714299392","post_url":"https://www.tumblr.com/blog/view/goodtransgirl/811675332714299392","notes":2615,"npd":9.8,"is_reblog":true,"added_content":false,"tags":[],"delta":159},{"id":"811671047692763136","post_url":"https://www.tumblr.com/blog/view/goodtransgirl/811671047692763136","notes":986,"npd":7.89,"is_reblog":true,"added_content":false,"tags":[],"delta":128},{"id":"811662364731686912","post_url":"https://www.tumblr.com/blog/view/goodtransgirl/811662364731686912","notes":84,"npd":0,"is_reblog":true,"added_content":false,"tags":[],"delta":0},{"id":"811658089673719808","post_url":"https://www.tumblr.com/blog/view/goodtransgirl/811658089673719808","notes":264454,"npd":171.4,"is_reblog":true,"added_content":false,"tags":[],"delta":2781},{"id":"811649408807665664","post_url":"https://www.tumblr.com/blog/view/goodtransgirl/811649408807665664","notes":29,"npd":0,"is_reblog":true,"added_content":false,"tags":[],"delta":0},{"id":"811645129188409344","post_url":"https://www.tumblr.com/blog/view/goodtransgirl/811645129188409344","notes":390,"npd":0,"is_reblog":true,"added_content":false,"tags":[],"delta":0},{"id":"811640860499460096","post_url":"https://www.tumblr.com/blog/view/goodtransgirl/811640860499460096","notes":4190,"npd":7.58,"is_reblog":true,"added_content":false,"tags":[],"delta":123},{"id":"811636972097552384","post_url":"https://www.tumblr.com/blog/view/goodtransgirl/811636972097552384","notes":859,"npd":0.25,"is_reblog":true,"added_content":false,"tags":[],"delta":4},{"id":"811632165407375360","post_url":"https://www.tumblr.com/blog/view/goodtransgirl/811632165407375360","notes":16249,"npd":22.31,"is_reblog":true,"added_content":false,"tags":["it me","oh look it me"],"delta":362},{"id":"811627895224172544","post_url":"https://www.tumblr.com/blog/view/goodtransgirl/811627895224172544","notes":1865,"npd":40.31,"is_reblog":true,"added_content":false,"tags":[],"delta":654},{"id":"811623493277024256","post_url":"https://www.tumblr.com/blog/view/goodtransgirl/811623493277024256","notes":15709,"npd":15.72,"is_reblog":true,"added_content":false,"tags":[],"delta":255},{"id":"811619208887713792","post_url":"https://www.tumblr.com/blog/view/goodtransgirl/811619208887713792","notes":988,"npd":0.68,"is_reblog":true,"added_content":false,"tags":[],"delta":11},{"id":"811617600466518016","post_url":"https://www.tumblr.com/blog/view/goodtransgirl/811617600466518016","notes":196,"npd":0.55,"is_reblog":true,"added_content":false,"tags":[],"delta":9},{"id":"811614941790552064","post_url":"https://www.tumblr.com/blog/view/goodtransgirl/811614941790552064","notes":187749,"npd":436.85,"is_reblog":true,"added_content":false,"tags":[],"delta":7088,"likes":88081,"reblogs":98995,"comments":0},{"id":"811610642509348864","post_url":"https://www.tumblr.com/blog/view/goodtransgirl/811610642509348864","notes":991,"npd":2.71,"is_reblog":true,"added_content":false,"tags":[],"delta":44},{"id":"811606644339408896","post_url":"https://www.tumblr.com/blog/view/goodtransgirl/811606644339408896","notes":14584,"npd":155.5,"is_reblog":true,"added_content":false,"tags":[],"delta":2523},{"id":"811601968870080512","post_url":"https://www.tumblr.com/blog/view/goodtransgirl/811601968870080512","notes":2993,"npd":15.35,"is_reblog":true,"added_content":false,"tags":[],"delta":249},{"id":"811597682646958080","post_url":"https://www.tumblr.com/blog/view/goodtransgirl/811597682646958080","notes":93,"npd":0.06,"is_reblog":true,"added_content":false,"tags":[],"delta":1},{"id":"811589009060102144","post_url":"https://www.tumblr.com/blog/view/goodtransgirl/811589009060102144","notes":21972,"npd":7.09,"is_reblog":true,"added_content":false,"tags":[],"delta":115},{"id":"811584767072059392","post_url":"https://www.tumblr.com/blog/view/goodtransgirl/811584767072059392","notes":40250,"npd":25.21,"is_reblog":true,"added_content":false,"tags":[],"delta":409},{"id":"811580454777110528","post_url":"https://www.tumblr.com/blog/view/goodtransgirl/811580454777110528","notes":1038,"npd":3.27,"is_reblog":true,"added_content":false,"tags":[],"delta":53},{"id":"811571774484512768","post_url":"https://www.tumblr.com/blog/view/goodtransgirl/811571774484512768","notes":133,"npd":0.18,"is_reblog":true,"added_content":false,"tags":[],"delta":3},{"id":"811567499644715008","post_url":"https://www.tumblr.com/blog/view/goodtransgirl/811567499644715008","notes":6354,"npd":31.19,"is_reblog":true,"added_content":false,"tags":["it me","oh look it me"],"delta":506},{"id":"811558813561929728","post_url":"https://www.tumblr.com/blog/view/goodtransgirl/811558813561929728","notes":5060,"npd":100.28,"is_reblog":true,"added_content":false,"tags":[],"delta":1627},{"id":"811554540543475712","post_url":"https://www.tumblr.com/blog/view/goodtransgirl/811554540543475712","notes":305623,"npd":76.79,"is_reblog":true,"added_content":false,"tags":[],"delta":1246},{"id":"811550151314440192","post_url":"https://www.tumblr.com/blog/view/goodtransgirl/811550151314440192","notes":1071,"npd":5.24,"is_reblog":true,"added_content":false,"tags":[],"delta":85},{"id":"811546199413932032","post_url":"https://www.tumblr.com/blog/view/goodtransgirl/811546199413932032","notes":1447,"npd":0.25,"is_reblog":true,"added_content":false,"tags":[],"delta":4},{"id":"811541568973602816","post_url":"https://www.tumblr.com/blog/view/goodtransgirl/811541568973602816","notes":1957,"npd":4.25,"is_reblog":true,"added_content":false,"tags":[],"delta":69},{"id":"811537293257097216","post_url":"https://www.tumblr.com/blog/view/goodtransgirl/811537293257097216","notes":113,"npd":1.73,"is_reblog":true,"added_content":false,"tags":[],"delta":28},{"id":"811532888895029248","post_url":"https://www.tumblr.com/blog/view/goodtransgirl/811532888895029248","notes":3909,"npd":11.89,"is_reblog":true,"added_content":false,"tags":[],"delta":193},{"id":"811528607829721088","post_url":"https://www.tumblr.com/blog/view/goodtransgirl/811528607829721088","notes":164,"npd":1.23,"is_reblog":true,"added_content":false,"tags":[],"delta":20},{"id":"811527003161477120","post_url":"https://www.tumblr.com/blog/view/goodtransgirl/811527003161477120","notes":196,"npd":0.55,"is_reblog":true,"added_content":false,"tags":[],"delta":9},{"id":"811520047038300160","post_url":"https://www.tumblr.com/blog/view/goodtransgirl/811520047038300160","notes":9011,"npd":3.82,"is_reblog":true,"added_content":false,"tags":[],"delta":62},{"id":"811516017313513472","post_url":"https://www.tumblr.com/blog/view/goodtransgirl/811516017313513472","notes":129,"npd":0.31,"is_reblog":true,"added_content":false,"tags":[],"delta":5},{"id":"811507086122958848","post_url":"https://www.tumblr.com/blog/view/goodtransgirl/811507086122958848","notes":778,"npd":3.94,"is_reblog":true,"added_content":false,"tags":[],"delta":64},{"id":"811502685630152704","post_url":"https://www.tumblr.com/blog/view/goodtransgirl/811502685630152704","notes":676,"npd":6.1,"is_reblog":true,"added_content":false,"tags":[],"delta":99},{"id":"811498425116950528","post_url":"https://www.tumblr.com/blog/view/goodtransgirl/811498425116950528","notes":5,"npd":0,"is_reblog":true,"added_content":false,"tags":[],"delta":0},{"id":"811494135353704448","post_url":"https://www.tumblr.com/blog/view/goodtransgirl/811494135353704448","notes":64273,"npd":19.97,"is_reblog":true,"added_content":false,"tags":[],"delta":324},{"id":"811481245357932544","post_url":"https://www.tumblr.com/blog/view/goodtransgirl/811481245357932544","notes":3202,"npd":6.66,"is_reblog":true,"added_content":false,"tags":[],"delta":108},{"id":"811476894844387328","post_url":"https://www.tumblr.com/blog/view/goodtransgirl/811476894844387328","notes":944,"npd":0.37,"is_reblog":true,"added_content":false,"tags":[],"delta":6},{"id":"811472499353272320","post_url":"https://www.tumblr.com/blog/view/goodtransgirl/811472499353272320","notes":11693,"npd":14.79,"is_reblog":true,"added_content":false,"tags":[],"delta":240},{"id":"811468222508498944","post_url":"https://www.tumblr.com/blog/view/goodtransgirl/811468222508498944","notes":98527,"npd":139.16,"is_reblog":true,"added_content":false,"tags":[],"delta":2258},{"id":"811459661539753985","post_url":"https://www.tumblr.com/blog/view/goodtransgirl/811459661539753985","notes":950,"npd":1.97,"is_reblog":true,"added_content":false,"tags":[],"delta":32},{"id":"811455544178196480","post_url":"https://www.tumblr.com/blog/view/goodtransgirl/811455544178196480","notes":862,"npd":0.8,"is_reblog":true,"added_content":false,"tags":["it me","oh look it me","trans stoner"],"delta":13},{"id":"811450983182909441","post_url":"https://www.tumblr.com/blog/view/goodtransgirl/811450983182909441","notes":13170,"npd":103.48,"is_reblog":true,"added_content":false,"tags":[],"delta":1679},{"id":"811446695772684289","post_url":"https://www.tumblr.com/blog/view/goodtransgirl/811446695772684289","notes":50271,"npd":25.15,"is_reblog":true,"added_content":false,"tags":[],"delta":408},{"id":"811442298721304577","post_url":"https://www.tumblr.com/blog/view/goodtransgirl/811442298721304577","notes":47207,"npd":228.47,"is_reblog":true,"added_content":false,"tags":[],"delta":3707},{"id":"811438057072017408","post_url":"https://www.tumblr.com/blog/view/goodtransgirl/811438057072017408","notes":953,"npd":7.58,"is_reblog":true,"added_content":false,"tags":[],"delta":123},{"id":"811436401851875328","post_url":"https://www.tumblr.com/blog/view/goodtransgirl/811436401851875328","notes":196,"npd":0.55,"is_reblog":true,"added_content":false,"tags":[],"delta":9},{"id":"811433739972493312","post_url":"https://www.tumblr.com/blog/view/goodtransgirl/811433739972493312","notes":603863,"npd":151.74,"is_reblog":true,"added_content":false,"tags":["shitposting","shitpost","meme","memes","retro meme","retro memes","tumblr classic","trans blog","transgender","sapphic","wlw","lgbtq","gay","mtf","transbian","lgbtqia","sapphic blog"],"delta":2462},{"id":"811429448216870912","post_url":"https://www.tumblr.com/blog/view/goodtransgirl/811429448216870912","notes":4070,"npd":15.59,"is_reblog":true,"added_content":false,"tags":[],"delta":253},{"id":"811425354406330368","post_url":"https://www.tumblr.com/blog/view/goodtransgirl/811425354406330368","notes":2462,"npd":10.11,"is_reblog":true,"added_content":false,"tags":[],"delta":164},{"id":"811420806569672704","post_url":"https://www.tumblr.com/blog/view/goodtransgirl/811420806569672704","notes":294108,"npd":107.36,"is_reblog":true,"added_content":false,"tags":[],"delta":1742},{"id":"811416509821911040","post_url":"https://www.tumblr.com/blog/view/goodtransgirl/811416509821911040","notes":676,"npd":6.1,"is_reblog":true,"added_content":false,"tags":[],"delta":99},{"id":"811411879016775680","post_url":"https://www.tumblr.com/blog/view/goodtransgirl/811411879016775680","notes":8,"npd":0,"is_reblog":true,"added_content":false,"tags":[],"delta":0},{"id":"811407866232766464","post_url":"https://www.tumblr.com/blog/view/goodtransgirl/811407866232766464","notes":6198,"npd":111.25,"is_reblog":true,"added_content":false,"tags":[],"delta":1805},{"id":"811403535199748097","post_url":"https://www.tumblr.com/blog/view/goodtransgirl/811403535199748097","notes":826,"npd":2.4,"is_reblog":true,"added_content":false,"tags":[],"delta":39},{"id":"811399256519917568","post_url":"https://www.tumblr.com/blog/view/goodtransgirl/811399256519917568","notes":3654,"npd":11.96,"is_reblog":true,"added_content":false,"tags":[],"delta":194},{"id":"811386316930629632","post_url":"https://www.tumblr.com/blog/view/goodtransgirl/811386316930629632","notes":63960,"npd":13.62,"is_reblog":true,"added_content":false,"tags":[],"delta":221},{"id":"811381903091548160","post_url":"https://www.tumblr.com/blog/view/goodtransgirl/811381903091548160","notes":1493,"npd":1.6,"is_reblog":true,"added_content":false,"tags":[],"delta":26},{"id":"811373333859926016","post_url":"https://www.tumblr.com/blog/view/goodtransgirl/811373333859926016","notes":8023,"npd":20.34,"is_reblog":true,"added_content":false,"tags":[],"delta":330},{"id":"811369061542969344","post_url":"https://www.tumblr.com/blog/view/goodtransgirl/811369061542969344","notes":18542,"npd":149.95,"is_reblog":true,"added_content":false,"tags":[],"delta":2433},{"id":"811365010235326464","post_url":"https://www.tumblr.com/blog/view/goodtransgirl/811365010235326464","notes":3870,"npd":1.05,"is_reblog":true,"added_content":false,"tags":[],"delta":17},{"id":"811360378799915008","post_url":"https://www.tumblr.com/blog/view/goodtransgirl/811360378799915008","notes":78824,"npd":6.96,"is_reblog":true,"added_content":false,"tags":[],"delta":113},{"id":"811356109305790464","post_url":"https://www.tumblr.com/blog/view/goodtransgirl/811356109305790464","notes":591,"npd":1.36,"is_reblog":true,"added_content":false,"tags":[],"delta":22},{"id":"811351702467903488","post_url":"https://www.tumblr.com/blog/view/goodtransgirl/811351702467903488","notes":36401,"npd":300.46,"is_reblog":true,"added_content":false,"tags":[],"delta":4875},{"id":"811347434353655808","post_url":"https://www.tumblr.com/blog/view/goodtransgirl/811347434353655808","notes":4249,"npd":66.5,"is_reblog":true,"added_content":false,"tags":[],"delta":1079},{"id":"811345792557268992","post_url":"https://www.tumblr.com/blog/view/goodtransgirl/811345792557268992","notes":196,"npd":0.55,"is_reblog":true,"added_content":false,"tags":[],"delta":9},{"id":"811343147714084864","post_url":"https://www.tumblr.com/blog/view/goodtransgirl/811343147714084864","notes":205,"npd":7.58,"is_reblog":true,"added_content":false,"tags":[],"delta":123},{"id":"811338848281952256","post_url":"https://www.tumblr.com/blog/view/goodtransgirl/811338848281952256","notes":310,"npd":1.23,"is_reblog":true,"added_content":false,"tags":[],"delta":20},{"id":"811332173503315968","post_url":"https://www.tumblr.com/blog/view/goodtransgirl/811332173503315968","notes":1690648,"npd":61.32,"is_reblog":true,"added_content":false,"tags":[],"delta":995},{"id":"811331304250621952","post_url":"https://www.tumblr.com/blog/view/goodtransgirl/811331304250621952","notes":777881,"npd":49.18,"is_reblog":true,"added_content":false,"tags":[],"delta":798},{"id":"811325909676244992","post_url":"https://www.tumblr.com/blog/view/goodtransgirl/811325909676244992","notes":2122,"npd":1.17,"is_reblog":true,"added_content":false,"tags":["been there done that","all three of us took turns","only I liked it best of the three","surrounded by girl","yes please"],"delta":19},{"id":"811321499838480384","post_url":"https://www.tumblr.com/blog/view/goodtransgirl/811321499838480384","notes":133,"npd":0,"is_reblog":true,"added_content":false,"tags":[],"delta":0},{"id":"811317226416242688","post_url":"https://www.tumblr.com/blog/view/goodtransgirl/811317226416242688","notes":1566,"npd":10.85,"is_reblog":true,"added_content":false,"tags":[],"delta":176},{"id":"811312929243873280","post_url":"https://www.tumblr.com/blog/view/goodtransgirl/811312929243873280","notes":249,"npd":0.12,"is_reblog":true,"added_content":false,"tags":[],"delta":2},{"id":"811308651982798848","post_url":"https://www.tumblr.com/blog/view/goodtransgirl/811308651982798848","notes":285,"npd":0.18,"is_reblog":true,"added_content":false,"tags":["i am so gay","omg im so gay"],"delta":3},{"id":"811299976069120000","post_url":"https://www.tumblr.com/blog/view/goodtransgirl/811299976069120000","notes":24858,"npd":21.88,"is_reblog":true,"added_content":false,"tags":[],"delta":355},{"id":"811295711864995840","post_url":"https://www.tumblr.com/blog/view/goodtransgirl/811295711864995840","notes":8073,"npd":267.54,"is_reblog":true,"added_content":false,"tags":[],"delta":4341,"likes":4802,"reblogs":2988,"comments":0},{"id":"811291301027905537","post_url":"https://www.tumblr.com/blog/view/goodtransgirl/811291301027905537","notes":30599,"npd":0.8,"is_reblog":true,"added_content":false,"tags":["shitposting","shitpost","meme","memes","retro meme","retro memes","tumblr classic","trans blog","transgender","sapphic","wlw","lgbtq","gay","mtf","transbian","lgbtqia","sapphic blog","fallout meme","fallout memes","fnv meme","fnv memes","fallout trans meme","fallout trans memes","fnv trans meme","fnv trans memes","trans meme","trans memes","lgbt meme","lgbt memes","queer meme"],"delta":13},{"id":"811287044596891648","post_url":"https://www.tumblr.com/blog/view/goodtransgirl/811287044596891648","notes":55262,"npd":77.35,"is_reblog":true,"added_content":false,"tags":[],"delta":1255},{"id":"811282776655642624","post_url":"https://www.tumblr.com/blog/view/goodtransgirl/811282776655642624","notes":2663,"npd":35.99,"is_reblog":true,"added_content":false,"tags":[],"delta":584},{"id":"811278410983882752","post_url":"https://www.tumblr.com/blog/view/goodtransgirl/811278410983882752","notes":111998,"npd":9.55,"is_reblog":true,"added_content":false,"tags":[],"delta":155},{"id":"811274137121292288","post_url":"https://www.tumblr.com/blog/view/goodtransgirl/811274137121292288","notes":290,"npd":1.97,"is_reblog":true,"added_content":false,"tags":[],"delta":32},{"id":"811269784268406784","post_url":"https://www.tumblr.com/blog/view/goodtransgirl/811269784268406784","notes":3393,"npd":13.81,"is_reblog":true,"added_content":false,"tags":[],"delta":224},{"id":"811268399512584192","post_url":"https://www.tumblr.com/blog/view/goodtransgirl/811268399512584192","notes":461914,"npd":50.78,"is_reblog":true,"added_content":false,"tags":["shitposting","shitpost","meme","memes","retro meme","retro memes","tumblr classic","trans blog","transgender","sapphic","wlw","lgbtq","gay","mtf","transbian","lgbtqia","sapphic blog"],"delta":824},{"id":"811261101699448832","post_url":"https://www.tumblr.com/blog/view/goodtransgirl/811261101699448832","notes":1261,"npd":0.31,"is_reblog":true,"added_content":false,"tags":[],"delta":5},{"id":"811257086367416320","post_url":"https://www.tumblr.com/blog/view/goodtransgirl/811257086367416320","notes":410506,"npd":265.76,"is_reblog":true,"added_content":false,"tags":["shitposting","shitpost","meme","memes","retro meme","retro memes","tumblr classic","trans blog","transgender","sapphic","wlw","lgbtq","gay","mtf","transbian","lgbtqia","sapphic blog"],"delta":4312},{"id":"811256828523659264","post_url":"https://www.tumblr.com/blog/view/goodtransgirl/811256828523659264","notes":2170,"npd":2.96,"is_reblog":true,"added_content":false,"tags":["it me"],"delta":48},{"id":"811255236600659968","post_url":"https://www.tumblr.com/blog/view/goodtransgirl/811255236600659968","notes":196,"npd":0.55,"is_reblog":true,"added_content":false,"tags":[],"delta":9},{"id":"811253898072506368","post_url":"https://www.tumblr.com/blog/view/goodtransgirl/811253898072506368","notes":4,"npd":0.06,"is_reblog":true,"added_content":false,"tags":[],"delta":1},{"id":"811252553981591552","post_url":"https://www.tumblr.com/blog/view/goodtransgirl/811252553981591552","notes":1434,"npd":3.39,"is_reblog":true,"added_content":false,"tags":[],"delta":55},{"id":"811249516156157952","post_url":"https://www.tumblr.com/blog/view/goodtransgirl/811249516156157952","notes":1654983,"npd":117.84,"is_reblog":true,"added_content":false,"tags":["none pizza with left beef","shitposting","shitpost","meme","memes","retro meme","retro memes","tumblr classic","trans blog","transgender","sapphic","wlw","lgbtq","gay","mtf","transbian","lgbtqia","sapphic blog"],"delta":1912},{"id":"811248260973985792","post_url":"https://www.tumblr.com/blog/view/goodtransgirl/811248260973985792","notes":845390,"npd":78.89,"is_reblog":true,"added_content":false,"tags":["shitposting","shitpost","meme","memes","tumblr classic","retro meme","retro memes","transgender","lgbtq","mtf","lgbtqia","transbian","sapphic blog","sapphic","wlw","gay","trans blog"],"delta":1280},{"id":"811244473166315520","post_url":"https://www.tumblr.com/blog/view/goodtransgirl/811244473166315520","notes":497,"npd":1.54,"is_reblog":true,"added_content":false,"tags":[],"delta":25},{"id":"811241999243083776","post_url":"https://www.tumblr.com/blog/view/goodtransgirl/811241999243083776","notes":113322,"npd":0.06,"is_reblog":true,"added_content":false,"tags":["shitposting","shitpost","meme","memes","retro meme","retro memes","tumblr classic","trans blog","transgender","sapphic","wlw","lgbtq","gay","mtf","transbian","lgbtqia","sapphic blog"],"delta":1}]}