{"id":"806127517145694208","type":"text","timestamp":1768783108,"post_url":"https://www.tumblr.com/blog/view/goodtransgirl/806127517145694208","is_reblog":true,"added_content":false,"tags":[],"reblog_ready":false,"body":"<p><a class=\"tumblr_blog\" href=\"https://forcefem-now.tumblr.com/post/805456106159849472/and-if-you-think-you-cant-lezz-out-because-youre\">forcefem-now</a>:</p><blockquote><p><a class=\"tumblr_blog\" href=\"https://dragongirlbunny.tumblr.com/post/805195139607920640/lezzing-out-is-basically-one-of-the-most-noble\">dragongirlbunny</a>:</p><blockquote><p>&ldquo;lezzing out&rdquo; is basically one of the most noble activities one can do</p></blockquote><p>And if you think you can&rsquo;t lezz out because you&rsquo;re &ldquo;not a girl&rdquo;, i promise you can be a girl</p></blockquote>","trail":[{"blog":{"name":"dragongirlbunny"},"post":{"id":"805195139607920640"}},{"blog":{"name":"forcefem-now"},"post":{"id":"805456106159849472"}}],"baseline_notes":13795,"baseline_ts":1774705101.464}