{"id":"806910082019409920","type":"text","timestamp":1769529420,"post_url":"https://www.tumblr.com/blog/view/goodtransgirl/806910082019409920","is_reblog":true,"added_content":false,"tags":[],"reblog_ready":false,"body":"<p><a class=\"tumblr_blog\" href=\"https://realtransfacts.tumblr.com/post/805748843339759616/may-your-body-change-into-a-more-comfortable\">realtransfacts</a>:</p><blockquote><p>May your body change into a more comfortable version of itself for you this year</p></blockquote>","trail":[{"blog":{"name":"realtransfacts"},"post":{"id":"805748843339759616"}}],"baseline_notes":4411,"baseline_ts":1774705101.464}