{"id":"807101813986869249","type":"text","timestamp":1769712270,"post_url":"https://www.tumblr.com/blog/view/goodtransgirl/807101813986869249","is_reblog":true,"added_content":false,"tags":[],"reblog_ready":false,"body":"<p><a class=\"tumblr_blog\" href=\"https://www.tumblr.com/blog/view/sweetfoolfemme/806472610924904448\">sweetfoolfemme</a>:</p><blockquote><p>forehead kisses and palm kisses and neck kisses and tummy kisses and cheek kisses and </p></blockquote>","trail":[{"blog":{"name":"sweetfoolfemme"},"post":{"id":"806472610924904448"}}],"baseline_notes":3926,"baseline_ts":1774705101.464}