{"id":"808524388972527616","type":"text","timestamp":1771068943,"post_url":"https://www.tumblr.com/blog/view/goodtransgirl/808524388972527616","is_reblog":true,"added_content":false,"tags":[],"reblog_ready":false,"body":"<p><a class=\"tumblr_blog\" href=\"https://www.tumblr.com/blog/view/kerry444-deactivated20260329/807490573697171456\">kerry444-deactivated20260329</a>:</p><blockquote><p>can i please play with your boobs while you tell me about your day </p></blockquote>","trail":[{"blog":{"name":"kerry444-deactivated20260329","active":false,"theme":{"header_full_width":946,"header_full_height":2048,"header_focus_width":778,"header_focus_height":437,"avatar_shape":"square","background_color":"#FBE6F4","body_font":"Helvetica Neue","header_bounds":"52,872,489,94","header_image":"https://64.media.tumblr.com/b672e342590115cf3e76bc60a817977d/164a11704ef9d9c6-5d/s946x2048/64b035d3b639c8b15053ba14e536dd8ed1dc9c31.jpg","header_image_focused":"https://64.media.tumblr.com/b672e342590115cf3e76bc60a817977d/164a11704ef9d9c6-5d/s2048x3072_c9937,2539,92178,23877/6d2863b51792de81c8a2b7c9887caab86dd1855d.jpg","header_image_poster":"","header_image_scaled":"https://64.media.tumblr.com/b672e342590115cf3e76bc60a817977d/164a11704ef9d9c6-5d/s2048x3072/6b22a1ba4dd40b168aae99f9f111a27ff59f1207.jpg","header_stretch":true,"link_color":"#E9CFE4","show_avatar":true,"show_description":true,"show_header_image":true,"show_title":true,"title_color":"#000000","title_font":"Gibson","title_font_weight":"bold"},"share_likes":false,"share_following":false,"can_be_followed":false},"post":{"id":"807490573697171456"},"content_raw":"<p>can i please play with your boobs while you tell me about your day </p>","content":"<p>can i please play with your boobs while you tell me about your day </p>","is_root_item":true}],"baseline_notes":3330,"baseline_ts":1774705101.464}