{"id":"808659202452127744","type":"text","timestamp":1771197512,"post_url":"https://www.tumblr.com/blog/view/goodtransgirl/808659202452127744","is_reblog":true,"added_content":false,"tags":[],"reblog_ready":false,"body":"<p><a class=\"tumblr_blog\" href=\"https://www.tumblr.com/blog/view/sapphic-dice/808124376348262400\">sapphic-dice</a>:</p><blockquote><p><a class=\"tumblr_blog\" href=\"https://www.tumblr.com/blog/view/keyboardsareforcoding/808124133467701248\">keyboardsareforcoding</a>:</p><blockquote><p><a class=\"tumblr_blog\" href=\"https://www.tumblr.com/blog/view/sapphic-dice/808123267014656000\">sapphic-dice</a>:</p><blockquote><p><a class=\"tumblr_blog\" href=\"https://www.tumblr.com/blog/view/localfae0225-deactivated2026032/808123227248410624\">localfae0225-deactivated2026032</a>:</p><blockquote><p><a class=\"tumblr_blog\" href=\"https://www.tumblr.com/blog/view/sapphic-dice/808105198883078144\">sapphic-dice</a>:</p><blockquote><p>Pretty women shouldn’t call me pretty, I’m gonna die </p></blockquote><p>But you are pretty</p></blockquote><p>Damn. </p><p>Can I get a second opinion? </p></blockquote><p>You are really pretty </p></blockquote><p>FUCK</p></blockquote>","trail":[{"blog":{"name":"sapphic-dice"},"post":{"id":"808105198883078144"}},{"blog":{"name":"localfae0225-deactivated2026032"},"post":{"id":"808123227248410624"}},{"blog":{"name":"sapphic-dice"},"post":{"id":"808123267014656000"}},{"blog":{"name":"keyboardsareforcoding"},"post":{"id":"808124133467701248"}},{"blog":{"name":"sapphic-dice"},"post":{"id":"808124376348262400"}}],"baseline_notes":169,"baseline_ts":1774705101.464}