{"id":"809056065392148480","type":"text","timestamp":1771575990,"post_url":"https://www.tumblr.com/blog/view/goodtransgirl/809056065392148480","is_reblog":true,"added_content":false,"tags":[],"reblog_ready":true,"body":"<p><a class=\"tumblr_blog\" href=\"https://www.tumblr.com/blog/view/apple3rst/806864005348130816\">apple3rst</a>:</p><blockquote><p>I’m so easy when it comes to a beautiful women </p></blockquote>","trail":[{"blog":{"name":"apple3rst","active":true,"theme":{"header_full_width":736,"header_full_height":414,"header_focus_width":735,"header_focus_height":413,"avatar_shape":"circle","background_color":"#F8E2E2","body_font":"Helvetica Neue","header_bounds":"0,735,413,0","header_image":"https://64.media.tumblr.com/63c84e0ea155b3014059267bbbe63294/d2f271cb9d3f28ee-52/s736x414/a9985a8f2174a3616bc11586edb53410afdc0a95.jpg","header_image_focused":"https://64.media.tumblr.com/63c84e0ea155b3014059267bbbe63294/d2f271cb9d3f28ee-52/s2048x3072_c0,0,99864,99758/0f33acdf23b91b454972341a784da3881e4ff595.jpg","header_image_poster":"","header_image_scaled":"https://64.media.tumblr.com/63c84e0ea155b3014059267bbbe63294/d2f271cb9d3f28ee-52/s2048x3072/92c4cddbefac6a5246ceaa398c6905a26306663c.jpg","header_stretch":true,"link_color":"#F9DCDC","show_avatar":true,"show_description":true,"show_header_image":true,"show_title":true,"title_color":"#9D8181","title_font":"Caslon FS","title_font_weight":"bold"},"share_likes":false,"share_following":false,"can_be_followed":true},"post":{"id":"806864005348130816"},"content_raw":"<p>I’m so easy when it comes to a beautiful women </p>","content":"<p>I&rsquo;m so easy when it comes to a beautiful women </p>","is_root_item":true}],"baseline_notes":32,"baseline_ts":1774705101.464}