{"id":"809353805103857664","type":"text","timestamp":1771859936,"post_url":"https://www.tumblr.com/blog/view/goodtransgirl/809353805103857664","is_reblog":true,"added_content":false,"tags":[],"reblog_ready":false,"body":"<p><a class=\"tumblr_blog\" href=\"https://www.tumblr.com/blog/view/domofdestruction/804319630854324224\">domofdestruction</a>:</p><blockquote><p>Need sleepy, sensual sex with no goals and no end. Just soft pleasure and skin to skin contact and slow kisses </p></blockquote>","trail":[{"blog":{"name":"domofdestruction","active":true,"theme":{"header_full_width":1170,"header_full_height":708,"avatar_shape":"circle","background_color":"#891818","body_font":"Helvetica Neue","header_bounds":"","header_image":"https://64.media.tumblr.com/113760fca589aff8a98621d1d8561eb3/aae084695f739b3b-17/s1170x708/44b677dffbf8fe4246a3aab4b965b26c089867c1.jpg","header_image_focused":"https://64.media.tumblr.com/113760fca589aff8a98621d1d8561eb3/aae084695f739b3b-17/s2048x3072/97782298a43c1bfbd61658f6aaab027aa87bc94d.jpg","header_image_poster":"","header_image_scaled":"https://64.media.tumblr.com/113760fca589aff8a98621d1d8561eb3/aae084695f739b3b-17/s2048x3072/97782298a43c1bfbd61658f6aaab027aa87bc94d.jpg","header_stretch":true,"link_color":"#000000","show_avatar":true,"show_description":true,"show_header_image":true,"show_title":false,"title_color":"#000000","title_font":"Gibson","title_font_weight":"bold"},"share_likes":false,"share_following":false,"can_be_followed":true},"post":{"id":"804319630854324224"},"content_raw":"<p>Need sleepy, sensual sex with no goals and no end. Just soft pleasure and skin to skin contact and slow kisses </p>","content":"<p>Need sleepy, sensual sex with no goals and no end. Just soft pleasure and skin to skin contact and slow kisses </p>","is_root_item":true}],"baseline_notes":2148,"baseline_ts":1774705101.464}