{"id":"812158501848793088","type":"text","timestamp":1774534704,"post_url":"https://www.tumblr.com/blog/view/goodtransgirl/812158501848793088","is_reblog":true,"added_content":false,"tags":[],"reblog_ready":false,"body":"<p><a class=\"tumblr_blog\" href=\"https://www.tumblr.com/blog/view/gazeldhazel/811462473615065088\">gazeldhazel</a>:</p><blockquote><p>google how to put girls who want me in my room</p></blockquote>","trail":[{"blog":{"name":"gazeldhazel","active":true,"theme":{"header_full_width":961,"header_full_height":909,"avatar_shape":"square","background_color":"#DDD5EC","body_font":"Helvetica Neue","header_bounds":"","header_image":"https://64.media.tumblr.com/a3bd39547cff46fb8bf1809e574f75ce/251ab0366c7d3880-04/s961x909/b0569bca73b092b9c02cac7e6294260ed875f0b7.jpg","header_image_focused":"https://64.media.tumblr.com/a3bd39547cff46fb8bf1809e574f75ce/251ab0366c7d3880-04/s2048x3072/44b6c0d0e49f80798abad7e195a497196f56b8e0.jpg","header_image_poster":"","header_image_scaled":"https://64.media.tumblr.com/a3bd39547cff46fb8bf1809e574f75ce/251ab0366c7d3880-04/s2048x3072/44b6c0d0e49f80798abad7e195a497196f56b8e0.jpg","header_stretch":true,"link_color":"#35276D","show_avatar":true,"show_description":true,"show_header_image":true,"show_title":true,"title_color":"#473652","title_font":"Sans Serif","title_font_weight":"bold"},"share_likes":false,"share_following":false,"can_be_followed":true},"post":{"id":"811462473615065088"},"content_raw":"<p>google how to put girls who want me in my room</p>","content":"<p>google how to put girls who want me in my room</p>","is_root_item":true}],"baseline_notes":276,"baseline_ts":1774705101.464}