{"id":"812473538028224512","type":"text","timestamp":1774835145,"post_url":"https://www.tumblr.com/blog/view/goodtransgirl/812473538028224512","is_reblog":true,"added_content":false,"tags":[],"reblog_ready":false,"body":"<p><a class=\"tumblr_blog\" href=\"https://www.tumblr.com/blog/view/girlydemise/762723841940291584\">girlydemise</a>:</p><blockquote><p>Pangea should happen again so all the cute girls can date properly</p></blockquote>","trail":[{"blog":{"name":"girlydemise"},"post":{"id":"762723841940291584"}}],"baseline_notes":2496,"baseline_ts":1774836437.495}