{"id":"812624454897303552","type":"text","timestamp":1774979071,"post_url":"https://www.tumblr.com/blog/view/goodtransgirl/812624454897303552","is_reblog":true,"added_content":false,"tags":[],"reblog_ready":false,"body":"<p><a class=\"tumblr_blog\" href=\"https://jarlskona-evilyoyo.tumblr.com/post/788917924509466624/everytime-i-see-something-gay-in-a-tv-show-and-i\">jarlskona-evilyoyo</a>:</p><blockquote><p>Everytime I see something gay in a tv show and I say to myself ‘wow that might be the gayest thing thats ever happened on tv!’ I have to remind myself that the actual gayest thing that has ever happened on television was the time on Xena Warrior Princess that Xena got Sappho to write Gabrielle a poem for her birthday and they used Sappho’s actual poem. </p><p>Which means that in the Xena universe, one of Sappho’s most famous remaining poems was one dedicated to Gabrielle from Xena. </p><p>And that’s pretty fucking gay. </p></blockquote>","trail":[{"blog":{"name":"jarlskona-evilyoyo"},"post":{"id":"788917924509466624"}}],"baseline_notes":3688,"baseline_ts":1774997996.795}