{"id":"812797369717604352","type":"text","timestamp":1775143975,"post_url":"https://www.tumblr.com/blog/view/goodtransgirl/812797369717604352","is_reblog":true,"added_content":false,"tags":[],"reblog_ready":false,"body":"<p><a class=\"tumblr_blog\" href=\"https://persephhonnne.tumblr.com/post/811451044058005504/im-sorry-im-a-pervert-now-hold-hands-with-me\">persephhonnne</a>:</p><blockquote><p>im sorry im a pervert, now hold hands with me please </p></blockquote>","trail":[{"blog":{"name":"persephhonnne"},"post":{"id":"811451044058005504"}}],"baseline_notes":2482,"baseline_ts":1775145661.212}